{"stat.chestOpened":4,"stat.walkOneCm":58441,"stat.useItem.minecraft.chest":2,"stat.leaveGame":1,"stat.craftItem.weapons_of_the_apocalypse.refinedblood":1,"stat.mineBlock.minecraft.cobblestone":1,"stat.furnaceInteraction":6,"stat.useItem.weapons_of_the_apocalypse.stimpack":1,"stat.jump":28,"stat.killEntity.iysuperleaper":2,"stat.fallOneCm":795,"stat.craftItem.jrftl.prepared_flesh":2,"stat.useItem.realistictorches.torch_lit":27,"stat.craftItem.minecraft.stone_slab2":0,"stat.crouchOneCm":160,"stat.useItem.betterwithmods.steel_pickaxe":19,"stat.craftItem.weapons_of_the_apocalypse.stimpack":1,"stat.craftItem.minecraft.iron_ingot":7,"stat.sprintOneCm":1588,"stat.useItem.biomesoplenty.plant_1":7,"stat.useItem.minecraft.stone_slab2":8,"stat.pickup.weapons_of_the_apocalypse.fleshmorph":3,"stat.craftingTableInteraction":5,"stat.pickup.minecraft.iron_ore":5,"stat.pickup.minecraft.rotten_flesh":2,"stat.damageTaken":275,"stat.pickup.minecraft.cobblestone":13,"stat.mobKills":3,"stat.craftItem.weapons_of_the_apocalypse.zombieblood":1,"stat.flyOneCm":11535,"stat.deaths":1,"stat.playOneMinute":23234,"stat.useItem.minecraft.stone_pickaxe":1,"stat.sneakTime":126,"stat.mineBlock.minecraft.iron_ore":5,"stat.killEntity.Zombie":1,"stat.timeSinceDeath":12356,"stat.useItem.minecraft.spawn_egg":6,"stat.mineBlock.minecraft.stone":14,"stat.craftItem.minecraft.leather":2}