{"stat.entityKilledBy.techguns.ArmySoldier":1,"stat.pickup.techguns.itemshared":2,"stat.walkOneCm":20016,"stat.pickup.techguns.revolver":1,"stat.useItem.weapons_of_the_apocalypse.sledgehammer":8,"stat.killEntity.techguns.Bandit":1,"stat.damageTaken":526,"stat.pickup.weapons_of_the_apocalypse.ration":3,"stat.mobKills":1,"stat.flyOneCm":77635,"stat.deaths":2,"stat.jump":20,"stat.playOneMinute":6102,"stat.fallOneCm":604,"stat.sneakTime":263,"stat.pickup.firstaid.bandage":1,"stat.damageDealt":915,"stat.crouchOneCm":329,"stat.timeSinceDeath":2935,"stat.useItem.weapons_of_the_apocalypse.steelpipe":14,"stat.pickup.realistictorches.matchbox":1,"stat.entityKilledBy.techguns.Bandit":1,"stat.pickup.toughasnails.canteen":1,"stat.sprintOneCm":938}